odoo8_addon_pos_product_template-8.0.0.2.0.99.dev14-py2.7-nspkg.pth
odoo8_addon_pos_product_template-8.0.0.2.0.99.dev14.dist-info/DESCRIPTION.rst
odoo8_addon_pos_product_template-8.0.0.2.0.99.dev14.dist-info/METADATA
odoo8_addon_pos_product_template-8.0.0.2.0.99.dev14.dist-info/RECORD
odoo8_addon_pos_product_template-8.0.0.2.0.99.dev14.dist-info/WHEEL
odoo8_addon_pos_product_template-8.0.0.2.0.99.dev14.dist-info/metadata.json
odoo8_addon_pos_product_template-8.0.0.2.0.99.dev14.dist-info/namespace_packages.txt
odoo8_addon_pos_product_template-8.0.0.2.0.99.dev14.dist-info/top_level.txt
odoo_addons/pos_product_template/__init__.py
odoo_addons/pos_product_template/__openerp__.py
odoo_addons/pos_product_template/demo/product_attribute_value.yml
odoo_addons/pos_product_template/demo/product_product.yml
odoo_addons/pos_product_template/demo/res_groups.yml
odoo_addons/pos_product_template/i18n/am.po
odoo_addons/pos_product_template/i18n/ar.po
odoo_addons/pos_product_template/i18n/bg.po
odoo_addons/pos_product_template/i18n/bs.po
odoo_addons/pos_product_template/i18n/ca.po
odoo_addons/pos_product_template/i18n/ca_ES.po
odoo_addons/pos_product_template/i18n/cs.po
odoo_addons/pos_product_template/i18n/da.po
odoo_addons/pos_product_template/i18n/de.po
odoo_addons/pos_product_template/i18n/el_GR.po
odoo_addons/pos_product_template/i18n/en_AU.po
odoo_addons/pos_product_template/i18n/en_GB.po
odoo_addons/pos_product_template/i18n/es.po
odoo_addons/pos_product_template/i18n/es_AR.po
odoo_addons/pos_product_template/i18n/es_CL.po
odoo_addons/pos_product_template/i18n/es_CO.po
odoo_addons/pos_product_template/i18n/es_CR.po
odoo_addons/pos_product_template/i18n/es_DO.po
odoo_addons/pos_product_template/i18n/es_EC.po
odoo_addons/pos_product_template/i18n/es_ES.po
odoo_addons/pos_product_template/i18n/es_MX.po
odoo_addons/pos_product_template/i18n/es_PY.po
odoo_addons/pos_product_template/i18n/es_VE.po
odoo_addons/pos_product_template/i18n/et.po
odoo_addons/pos_product_template/i18n/eu.po
odoo_addons/pos_product_template/i18n/fa.po
odoo_addons/pos_product_template/i18n/fi.po
odoo_addons/pos_product_template/i18n/fr.po
odoo_addons/pos_product_template/i18n/fr_CA.po
odoo_addons/pos_product_template/i18n/fr_CH.po
odoo_addons/pos_product_template/i18n/fr_FR.po
odoo_addons/pos_product_template/i18n/gl.po
odoo_addons/pos_product_template/i18n/he.po
odoo_addons/pos_product_template/i18n/hi.po
odoo_addons/pos_product_template/i18n/hr.po
